{
    "editor-searchable-dropdowns/createBroadcast": "建立廣播訊息 {name}",
    "editor-searchable-dropdowns/createGlobalList": "建立全域清單 {name}",
    "editor-searchable-dropdowns/createGlobalVariable": "建立全域變數 {name} ",
    "editor-searchable-dropdowns/createLocalList": "建立區域清單 {name}",
    "editor-searchable-dropdowns/createLocalVariable": "建立區域變數 {name}",
    "editor-devtools/copy-all": "複製全部",
    "editor-devtools/copy-block": "複製積木",
    "editor-devtools/cut-block": "剪下積木",
    "editor-devtools/lists": "清單",
    "editor-devtools/make-space": "騰出空間",
    "editor-devtools/paste": "貼上",
    "editor-devtools/replace": "將這個角色上的變數 {name} 全部替換成：",
    "editor-devtools/swap": "替換角色中的所有{var}",
    "editor-devtools/var-not-exist": "這個變數不存在…",
    "editor-devtools/variables": "變數",
    "forum-search/error": "讀取 ScratchDB 時發生錯誤！",
    "forum-search/last-edited-by": "最後修改者為 {username} ({datetime})",
    "forum-search/loading": "加載中...",
    "forum-search/newest": "最新",
    "forum-search/none": "你的搜尋沒有結果",
    "forum-search/oldest": "最早",
    "forum-search/posts-here": "用戶在這裡發文",
    "forum-search/posts-sitewide": "用戶在全域發文",
    "forum-search/relevance": "關聯",
    "forum-search/username": "用戶名稱：",
    "scratch-notifier/clear": "標記為已讀",
    "scratch-notifier/notif-comment": "新的 Scratch 評論",
    "scratch-notifier/notif-fav": "{actor}收藏你的專案{title}",
    "scratch-notifier/notif-follow": "{actor}正在關注你",
    "scratch-notifier/notif-forum": "在討論區有新的討論串{title}",
    "scratch-notifier/notif-generic": "新的Scratch訊息",
    "scratch-notifier/notif-host": "{actor}已讓你成為創作坊「{title}」的主辦人。",
    "scratch-notifier/notif-invite": "{actor}邀請你策展創作坊{title}",
    "scratch-notifier/notif-love": "{actor}喜愛你的專案{title}",
    "scratch-notifier/notif-own-profile-reply": "{actor}在你的個人資訊頁上回應",
    "scratch-notifier/notif-own-profile-reply-other": "{actor}在你的個人資訊頁上回應了評論{commentee}",
    "scratch-notifier/notif-own-project": "{actor}在你的專案{title}評論",
    "scratch-notifier/notif-own-project-reply": "{actor}在你的專案{title}上回應評論{commentee}",
    "scratch-notifier/notif-profile": "{actor}在你的個人資訊頁上評論",
    "scratch-notifier/notif-profile-reply": "{actor}在{title}的個人資訊頁上回應",
    "scratch-notifier/notif-project-reply": "{actor}在你的專案{title}上回應",
    "scratch-notifier/notif-promotion": "{actor} 提升你成為創作坊 {title} 的管理員。",
    "scratch-notifier/notif-studio": "創作坊{title}今日有新的動態",
    "scratch-notifier/notif-studio-reply": "{actor}在創作坊{title}上回應",
    "scratch-notifier/open": "打開訊息頁面",
    "scratch-notifier/st": "Scratch 的團隊成員",
    "scratch-messaging/cancel": "取消",
    "scratch-messaging/chars-left": "{num, plural, other {剩餘 # 個字元}}",
    "scratch-messaging/comment-cannot-post-for": "{mins, plural, other {您被禁止發表評論 # 分鐘}}",
    "scratch-messaging/comment-error-down": "Scratch 伺服器目前有些問題。請稍候再試。",
    "scratch-messaging/comment-error-empty": "評論內容不可以是空的。",
    "scratch-messaging/comment-error-filterbot-chat": "Scratch 的過濾機器人阻擋了你發送的評論，因為你的內容提及聊天網站或社群媒體。",
    "scratch-messaging/comment-error-filterbot-generic": "Scratch 的過濾機器人阻擋了你發送的評論，因為你違反了社群規章。",
    "scratch-messaging/comment-error-filterbot-spam": "Scratch 的過濾機器人阻擋了你發送的評論，因為你發出的可能是不當內容。",
    "scratch-messaging/comment-error-ratelimit": "你發文的頻率太高了，請稍候片刻再發文。",
    "scratch-messaging/comment-error-reply-limit": "創作坊的每個評論下不能有超過 25 個回應。",
    "scratch-messaging/comment-mute": "Scratch 的過濾機器人將你禁言了，因為你的上個評論可能違反了社群規章。",
    "scratch-messaging/copy": "複製",
    "scratch-messaging/curate-invite": "{actor} 已邀請你策展 {title}",
    "scratch-messaging/delete": "刪除",
    "scratch-messaging/delete-confirm": "點擊以確認刪除",
    "scratch-messaging/delete-error": "刪除評論時出錯 - 你必須有權限才能這麼做。",
    "scratch-messaging/deleted": "[已刪除]",
    "scratch-messaging/deleting": "正在刪除評論…",
    "scratch-messaging/dismiss": "忽略",
    "scratch-messaging/follows": "關注者",
    "scratch-messaging/forum": "討論區動態",
    "scratch-messaging/forum-new-post": "討論串 {title} 有新的發文",
    "scratch-messaging/loading": "正在加載訊息...",
    "scratch-messaging/loading-comments": "正在讀取評論…",
    "scratch-messaging/logged-out": "無法存取訊息。",
    "scratch-messaging/logged-out-link": "請先登入 Scratch。",
    "scratch-messaging/mark-as-read": "標記訊息為已讀",
    "scratch-messaging/marked-as-read": "標記為已讀",
    "scratch-messaging/network-error": "無法存取伺服器，請檢查你的網路連線。",
    "scratch-messaging/new-activity": "{title} 有新的動態",
    "scratch-messaging/no-unread": "無未讀訊息",
    "scratch-messaging/open-messages": "打開訊息頁面",
    "scratch-messaging/open-new-tab": "以新頁籤開啟評論",
    "scratch-messaging/others-profile": "{username}的個人資訊",
    "scratch-messaging/popup-title": "Scratch Addons - 訊息",
    "scratch-messaging/post": "發文",
    "scratch-messaging/posting": "正在發文…",
    "scratch-messaging/reload": "重新讀取",
    "scratch-messaging/remixes": "改編",
    "scratch-messaging/reply": "回應",
    "scratch-messaging/report-bug": "請向我們回去以下錯誤代碼：",
    "scratch-messaging/send-error": "發送評論時出錯了",
    "scratch-messaging/server-error": "無法存取伺服器，請稍候再試。",
    "scratch-messaging/settings": "Scratch Addons 設定",
    "scratch-messaging/show-more": "顯示更多",
    "scratch-messaging/st": "Scratch 的團隊成員",
    "scratch-messaging/stMessages": "來自 Scratch 團隊的訊息",
    "scratch-messaging/studio": "創作坊：{title}",
    "scratch-messaging/studio-activity": "創作坊動態",
    "scratch-messaging/studio-host-transfer": "{actor}已讓你成為創作坊「{title}」的主辦人。",
    "scratch-messaging/studio-host-transfers": "創作坊主辦人移轉",
    "scratch-messaging/studio-invites": "創作坊的邀請",
    "scratch-messaging/studio-promotion": "{actor} 提升你成為創作坊 {title} 的管理員。",
    "scratch-messaging/studio-promotions": "創作坊推薦",
    "scratch-messaging/unknown-fatal-error": "讀取時發生錯誤。",
    "scratch-messaging/your-profile": "你的個人資料",
    "progress-bar/loading-assets": "正在加載資源 ({loaded}/{loading})...",
    "progress-bar/loading-project": "正在載入專案數據…",
    "full-signature/load-more": "顯示更多",
    "search-profile/profile": "個人資訊",
    "cloud-games/add-project": "添加這個專案",
    "cloud-games/add-project-desc": "點擊以將專案加入到遊戲清單。",
    "cloud-games/add-studio": "添加這個創作坊",
    "cloud-games/add-studio-desc": "點擊以將創作坊加入到遊戲清單。",
    "cloud-games/added": "添加完畢！",
    "cloud-games/addon-settings": "選項",
    "cloud-games/change-display": "你可以在{settings}上選擇要顯示的專案或創作坊。",
    "cloud-games/change-display-2": "你還可以在專案或創作坊頁面上，展開擴充功能的面板，然後在遊戲頁籤上點擊「添加這個專案」或「添加這個創作坊」按鈕。",
    "cloud-games/change-display-open": "你也可以點擊下方的「{buttonName}」，在目前的頁面中添加。",
    "cloud-games/fetch-error": "找不到這個專案使用的雲端變數：",
    "cloud-games/general-error": "無法載入專案。",
    "cloud-games/loading": "正在載入…",
    "cloud-games/no-projects": "沒有可顯示的專案。",
    "cloud-games/no-users": "沒有人在遊戲中",
    "cloud-games/popup-title": "Scratch Addons - 雲端變數遊戲",
    "cloud-games/server-error": "好像是 Scratch 伺服器的問題。",
    "studio-tools/401": "呃…看來你還不能這樣做，請確認你已登入。",
    "studio-tools/added-by": "來自 Scratch Addons 的擴充功能",
    "studio-tools/invalid-username": "用戶名稱無效。",
    "studio-tools/leave": "退出",
    "studio-tools/leave-confirm": "確定要退出這個創作坊？",
    "studio-tools/leave-new": "退出創作坊",
    "studio-tools/max-managers-reached": "這個創作坊已超出管理員最多 {max} 人的限制。",
    "studio-tools/not-curator": "這個用戶不是策展員。",
    "studio-tools/promote-btn": "提升",
    "studio-tools/promote-new": "提升策展員",
    "studio-tools/promoted": "已提升 {username} 成為管理者。",
    "studio-tools/remove-btn": "移除",
    "studio-tools/remove-new": "移除策展員",
    "studio-tools/removed": "已從創作坊移除 {username} 。",
    "studio-tools/server-down": "Scratch 伺服器好像掛了！",
    "studio-tools/too-many-managers": "在推薦之前你必須刪除一些管理員。",
    "studio-tools/unknown-error": "出了一些問題，麻煩再試一次。",
    "last-edit-tooltip/modified": "最後修改於 {date}",
    "last-edit-tooltip/shared": "分享於 {date}",
    "infinite-scroll/page-num": "{page}頁面",
    "clones/clones": "分身數：{cloneCount}",
    "editor-messages/messages": "訊息",
    "pause/pause": "暫停",
    "animated-thumb/added-by": "來自 Scratch Addons 的擴充功能",
    "animated-thumb/close": "關閉",
    "animated-thumb/error": "縮圖上傳失敗。",
    "animated-thumb/gif": "帶有動畫的縮圖在 Scratch 網頁上可能無法顯示，確定要上傳嗎？",
    "animated-thumb/if-unsuccessful": "這不是你上傳的圖像嗎？可能是 Scratch 伺服器的問題，請稍候再試一次。",
    "animated-thumb/server-error": "縮圖無法上傳，可能是伺服器錯誤導致，請稍候再試一次。",
    "animated-thumb/set-thumbnail": "設定縮圖",
    "animated-thumb/successful": "縮圖上傳成功。",
    "animated-thumb/too-big": "檔案太大了。",
    "live-featured-project/change-featured": "變更特色專案",
    "project-info/script": "{num, plural, other {# 個積木}}",
    "project-info/sprite": "{num, plural, other {# 個角色}}",
    "confirm-actions/accept-invite": "接受邀請",
    "confirm-actions/cancelcomment": "確定要取消評論？",
    "confirm-actions/cancelcomment-title": "取消評論",
    "confirm-actions/closetopic": "確定要關閉這個討論主題？",
    "confirm-actions/closetopic-title": "關閉討論主題",
    "confirm-actions/follow": "確定要關注這個用戶？",
    "confirm-actions/joinstudio": "確定要加入這個創作坊？",
    "confirm-actions/no": "否",
    "confirm-actions/removeproject": "確定要刪除這個專案？",
    "confirm-actions/removeproject-title": "刪除專案",
    "confirm-actions/unfollow": "確定要取消關注此用戶？",
    "confirm-actions/unshare": "確定要取消分享？",
    "confirm-actions/yes": "是",
    "block-switching/control_forever": "重複無限次",
    "block-switching/control_if": "如果",
    "block-switching/control_if_else": "如果…否則",
    "block-switching/control_repeat_until": "等待直到",
    "block-switching/control_wait_until": "等待直到",
    "block-switching/data_changevariableby": "變數改變",
    "block-switching/data_hidelist": "清單隱藏",
    "block-switching/data_hidevariable": "變數隱藏",
    "block-switching/data_insertatlist": "插入項目",
    "block-switching/data_replaceitemoflist": "替換項目",
    "block-switching/data_setvariableto": "變數設為",
    "block-switching/data_showlist": "清單顯示",
    "block-switching/data_showvariable": "變數顯示",
    "block-switching/debugger_error": "錯誤",
    "block-switching/debugger_log": "紀錄",
    "block-switching/debugger_warn": "警告",
    "block-switching/event_broadcast": "廣播訊息",
    "block-switching/event_broadcastandwait": "廣播訊息並等待",
    "block-switching/looks_backdropnumbername": "背景編號或名稱",
    "block-switching/looks_changeeffectby": "圖像效果改變",
    "block-switching/looks_changesizeby": "尺寸改變",
    "block-switching/looks_costumenumbername": "造型編號或名稱",
    "block-switching/looks_hide": "隱藏",
    "block-switching/looks_nextbackdrop": "背景換成下一個",
    "block-switching/looks_nextcostume": "造型換成下一個",
    "block-switching/looks_say": "說出",
    "block-switching/looks_sayforsecs": "說出持續",
    "block-switching/looks_seteffectto": "圖像效果設為",
    "block-switching/looks_setsizeto": "尺寸設為",
    "block-switching/looks_show": "顯示",
    "block-switching/looks_switchbackdropto": "背景換成",
    "block-switching/looks_switchbackdroptoandwait": "背景換成並等待",
    "block-switching/looks_think": "想著",
    "block-switching/looks_thinkforsecs": "想著持續",
    "block-switching/motion_changexby": "x 改變",
    "block-switching/motion_changeyby": "y 改變",
    "block-switching/motion_setx": "x 設為",
    "block-switching/motion_sety": "y 設為",
    "block-switching/motion_turnleft": "左轉",
    "block-switching/motion_turnright": "右轉",
    "block-switching/motion_xposition": "x  座標",
    "block-switching/motion_yposition": "y 座標",
    "block-switching/music_changeTempo": "演奏速度改變",
    "block-switching/music_setTempo": "演奏速度設為",
    "block-switching/operator_and": "且",
    "block-switching/operator_mod": "取餘數",
    "block-switching/operator_or": "或",
    "block-switching/pen_changePenColorParamBy": "參數改變",
    "block-switching/pen_changePenHueBy": "顏色改變",
    "block-switching/pen_changePenShadeBy": "陰影改變",
    "block-switching/pen_changePenSizeBy": "筆跡寬度改變",
    "block-switching/pen_penDown": "下筆",
    "block-switching/pen_penUp": "停筆",
    "block-switching/pen_setPenColorParamTo": "參數設為",
    "block-switching/pen_setPenHueToNumber": "顏色設為",
    "block-switching/pen_setPenShadeToNumber": "陰影設為",
    "block-switching/pen_setPenSizeTo": "筆跡寬度設為",
    "block-switching/sensing_mousex": "鼠標的 x",
    "block-switching/sensing_mousey": "鼠標的 y",
    "block-switching/sound_changeeffectby": "聲音效果改變",
    "block-switching/sound_changevolumeby": "音量改變",
    "block-switching/sound_play": "播放音效",
    "block-switching/sound_playuntildone": "播放音效直到結束",
    "block-switching/sound_seteffectto": "聲音效果設為",
    "block-switching/sound_setvolumeto": "音量設為",
    "my-ocular/add-reaction": "用 ocular 來回應這個發文",
    "my-ocular/status-hover": "這是來自 ocular 的一個自訂狀態功能。你可以在 https://ocular.jeffalo.net/dashboard 設置你自己的。",
    "my-ocular/view-on-ocular": "在 ocular 上檢視發文",
    "mediarecorder/cancel": "取消",
    "mediarecorder/click-flag": "正在等待…",
    "mediarecorder/option-title": "錄製設定",
    "mediarecorder/record-audio-description": "這不包括文字轉語音的聲音。",
    "mediarecorder/record-until-stop-disabled": "你必須啟用「{afterFlagOption}」才可以設定這個項目。",
    "mediarecorder/start": "開始",
    "mediarecorder/starting-in": "錄影倒數 {secs}...",
    "mediarecorder/stop": "停止錄影",
    "color-picker/hex": "hex 色碼",
    "onion-skinning/behind": "在後面",
    "onion-skinning/front": "在前面",
    "onion-skinning/layering": "圖層排列",
    "onion-skinning/merge": "合併",
    "onion-skinning/mode": "顯示模式",
    "onion-skinning/next": "下一個造型",
    "onion-skinning/opacity": "透明度（%）",
    "onion-skinning/opacityStep": "透明漸進（%）",
    "onion-skinning/previous": "上一個造型",
    "onion-skinning/settings": "描圖紙設定",
    "onion-skinning/tint": "染色",
    "onion-skinning/toggle": "描圖紙顯示切換",
    "data-category-tweaks-v2/for-all-sprites": "適用於所有角色：",
    "data-category-tweaks-v2/for-this-sprite-only": "僅適用於當前角色：",
    "data-category-tweaks-v2/list-category": "清單",
    "hide-flyout/lock": "固定工具箱",
    "hide-flyout/unlock": "取消固定工具箱",
    "longer-wiwo/left": "{number, plural, other {剩餘 # 個字元}}",
    "show-bbcode/loading": "正在讀取…",
    "show-bbcode/source-button": "檢視代碼",
    "show-bbcode/source-button-active": "檢視發文",
    "show-bbcode/source-button-tooltip": "顯示這則發文的 BBCode。",
    "copy-message-link/copied": "複製完畢！",
    "copy-message-link/copyLink": "複製連結",
    "variable-manager/for-all-sprites": "所有角色使用的變數",
    "variable-manager/for-this-sprite": "僅這個角色使用的變數",
    "variable-manager/search": "搜尋",
    "variable-manager/variables": "變數",
    "folders/add-to-folder": "放進資料夾：{folder}",
    "folders/closed-folder": "資料夾",
    "folders/confirm-backpack-folder": "將整個資料夾放進背包？",
    "folders/create-folder": "創建資料夾",
    "folders/name-not-allowed": "無效的資料夾名稱",
    "folders/name-prompt": "資料夾名稱：",
    "folders/name-prompt-title": "創建資料夾",
    "folders/open-folder": "已開啟",
    "folders/remove-folder": "移除資料夾",
    "folders/remove-from-folder": "移出資料夾",
    "folders/rename-folder": "更名資料夾",
    "folders/rename-folder-prompt": "將資料夾重新命名為：",
    "folders/rename-folder-prompt-title": "重新命名資料夾",
    "message-filters/comment": "評論",
    "message-filters/favorite": "收藏",
    "message-filters/follow": "關注",
    "message-filters/forum": "討論區動態",
    "message-filters/invite": "創作坊邀請",
    "message-filters/love": "喜愛",
    "message-filters/messages": "顯示訊息類別：",
    "message-filters/promotion": "創作坊晉升",
    "message-filters/remix": "改編",
    "message-filters/studio": "創作坊動態",
    "2d-color-picker/shade": "陰影",
    "gamepad/axes-a-b": "軸 {a} 與 {b}",
    "gamepad/axis-arrows": "方向鍵",
    "gamepad/axis-cursor": "滑鼠游標",
    "gamepad/axis-custom": "自訂",
    "gamepad/axis-none": "無",
    "gamepad/browser-support": "這個瀏覽器和操作系統有些已知錯誤，可能使這個插件難以使用，如果你碰到了一些問題，請試試其它的瀏覽器。",
    "gamepad/button-n": "按鈕 {n}",
    "gamepad/clear": "清空所有控制設置",
    "gamepad/config-header": "這個註解包含第三方工具或網站（如 https://turbowarp.org/）中的遊戲手柄配置。\n請勿手動修改",
    "gamepad/key-click": "點擊",
    "gamepad/key-down": "向下鍵",
    "gamepad/key-enter": "Enter 鍵",
    "gamepad/key-left": "向左鍵",
    "gamepad/key-none": "（無）",
    "gamepad/key-right": "向右鍵",
    "gamepad/key-space": "空白鍵",
    "gamepad/key-up": "向上鍵",
    "gamepad/keyinput-title": "點擊並按下一個鍵或單擊更改按鈕。ESC 鍵可取消。返回鍵或 Delete 鍵可刪除。",
    "gamepad/no-controllers": "未檢測到遊戲手柄，請在連接後再按一次按鈕。",
    "gamepad/reset": "重設所有控制設置到專案預設值",
    "gamepad/settings": "遊戲手柄設置",
    "better-img-uploads/upload": "高清圖片上傳",
    "debugger/block-breakpoint": "中斷點",
    "debugger/block-error": "錯誤 %s",
    "debugger/block-log": "記錄 %s",
    "debugger/block-warn": "警告 %s",
    "debugger/cannot-pause-player": "中斷點積木只能在編輯器中使用。",
    "debugger/clear": "清除",
    "debugger/clone-of": "{sprite}的分身",
    "debugger/close": "關閉",
    "debugger/console": "紀錄",
    "debugger/debug": "偵錯",
    "debugger/empty-string": "（空字串）",
    "debugger/enter-format": "輸入匯出格式：",
    "debugger/export": "匯出",
    "debugger/export-desc": "按住 Shift 鍵並點擊以自訂匯出格式",
    "debugger/icon-error": "錯誤",
    "debugger/icon-warn": "警告",
    "debugger/log-msg-broadcasted": "廣播了訊息{broadcast}",
    "debugger/log-msg-clone-cap": "創建{sprite}的分身時失敗，分身的創建不能超過 300 個。",
    "debugger/log-msg-clone-created": "建立了{sprite}的分身。",
    "debugger/log-msg-flag-clicked": "綠旗被點擊。",
    "debugger/no-logs": "沒有可顯示的紀錄。",
    "debugger/no-threads-running": "沒有運行中的執行緒。",
    "debugger/performance-clonecount-graph-tooltip": "分身：{clones}",
    "debugger/performance-clonecount-title": "分身",
    "debugger/performance-framerate-graph-tooltip": "幀率：{fps}",
    "debugger/performance-framerate-title": "幀率",
    "debugger/step": "步進",
    "debugger/step-desc": "執行一個積木",
    "debugger/tab-logs": "紀錄",
    "debugger/tab-performance": "效能",
    "debugger/tab-threads": "執行緒",
    "debugger/thread": "執行緒 {id}",
    "debugger/unknown-sprite": "（未知角色）",
    "debugger/unpause": "繼續",
    "studio-followers/button": "瀏覽關注者",
    "studio-followers/fetch-error": "呃…看來你還不能這樣做，請確認你已登入。",
    "studio-followers/followers": "關注者",
    "studio-followers/following": "正在關注",
    "studio-followers/modal-title": "邀請關注者加入創作坊",
    "forum-toolbar/center": "置中",
    "forum-toolbar/code": "代碼",
    "forum-toolbar/color": "顏色",
    "forum-toolbar/google": "Google 搜尋",
    "forum-toolbar/link": "連結至：",
    "forum-toolbar/prompt-code": "要高亮的程式語言：",
    "forum-toolbar/prompt-color": "顏色：",
    "forum-toolbar/prompt-dictionary": "英文單字：",
    "forum-toolbar/prompt-google": "所搜尋的關鍵字：",
    "forum-toolbar/prompt-wiki": "在 Scratch 維基百科上的標題：",
    "forum-toolbar/prompt-wp": "在維基百科上的標題：",
    "forum-toolbar/wiki": "Scratch 維基百科",
    "forum-toolbar/wp": "維基百科",
    "turbowarp-player/confirmation": "確定要切換到程式頁面？TurboWarp 編譯器將會停止。",
    "name-backpack-items/prompt": "給這個程式一個名稱：",
    "forum-copy-code/copy-code": "複製代碼",
    "editor-unshare-button/unshare-button": "取消分享",
    "editor-unshare-button/unshare-msg": "確定不要分享這個專案？",
    "editor-extra-keys/enter-key": "Enter",
    "forum-id/add-btn": "帶樓層引用",
    "move-to-top-bottom/bottom": "移至最下面",
    "move-to-top-bottom/top": "移至最上面",
    "search-my-stuff/end-header": "這是目前找到的全部內容。",
    "search-my-stuff/end-tip": "如果找不到你想要的，請檢查是不是字詞有錯，你也可以換個關鍵字詞來搜索。",
    "search-my-stuff/load-more-header": "這是目前找到的全部內容。",
    "search-my-stuff/load-more-tip": "如果找不到你想要的，可以試著載入更多內容，或者換個搜尋條件。\n如果搜尋結果太多，建議你用更精確的條件搜索。",
    "search-my-stuff/no-results-header": "找不到你任何相關的內容。",
    "search-my-stuff/no-results-tip": "檢查是否有錯別字，或者你可以換個字詞搜索。",
    "search-my-stuff/progress-header": "正在搜尋…",
    "search-my-stuff/progress-tip": "{number, plural, other {已找到 # 個項目}}",
    "search-my-stuff/project-placeholder": "搜尋專案",
    "search-my-stuff/search-by": "搜尋條件",
    "search-my-stuff/studio-placeholder": "搜尋創作坊",
    "search-my-stuff/trash-placeholder": "搜尋回收項目",
    "emoji-picker/show-less": "顯示較少",
    "emoji-picker/show-more": "顯示更多",
    "swap-local-global/cant-convert-cloud": "無法轉換，雲端變數不能被轉換成「僅適用當前角色」。",
    "swap-local-global/cant-convert-conflict": "無法轉換，因為會和其它角色中相同名稱的變數衝突：{sprites}",
    "swap-local-global/cant-convert-stage": "舞台不能有「僅適用當前角色」的變數。",
    "swap-local-global/cant-convert-to-local": "無法轉換，因為有其它角色也在使用這個變數：{sprites}",
    "swap-local-global/cant-convert-used-elsewhere": "無法轉換，因為有另一個角色也在使用這個變數：{sprite}",
    "swap-local-global/edit": "編輯屬性：",
    "swap-local-global/edit-list-header": "編輯清單",
    "swap-local-global/edit-list-option": "編輯清單",
    "swap-local-global/edit-variable-header": "編輯變數",
    "swap-local-global/edit-variable-option": "編輯變數",
    "swap-local-global/to-global": "轉換成「適用於所有角色」",
    "swap-local-global/to-local": "轉換成「僅適用當前角色」",
    "block-count/blocks": "{num, plural, other {# 個程式積木}}",
    "search-sprites/placeholder": "搜尋角色…",
    "hide-signatures/hide": "隱藏簽名",
    "hide-signatures/show": "顯示簽名",
    "one-click-studio-invites/accept": "接受邀請",
    "one-click-studio-invites/accepted": "已接受邀請",
    "one-click-studio-invites/failed": "無法將你添加到創作坊",
    "opacity-slider/opacity": "透明度",
    "find-bar/find-placeholder": "查找 (Ctrl+F)",
    "paint-snap/off": "關",
    "paint-snap/on": "開",
    "rename-broadcasts/RENAME_BROADCAST": "重新命名訊息",
    "rename-broadcasts/RENAME_BROADCAST_MODAL_TITLE": "重新命名訊息",
    "rename-broadcasts/RENAME_BROADCAST_TITLE": "將所有“{name}”消息重命名為：",
    "middle-click-popup/start-typing": "開始打字...",
    "hide-stage/hide-stage": "隱藏舞台"
}